LICENSE
MANIFEST.in
README.md
setup.py
spycial/__init__.py
spycial/constants.py
spycial/digamma.py
spycial/e1.py
spycial/ei.py
spycial/erf.py
spycial/erfinv.py
spycial/evalpoly.py
spycial/fma.py
spycial/gamma.py
spycial/lanczos.py
spycial/lgamma.py
spycial/settings.py
spycial/test_utilities.py
spycial/trig.py
spycial/zeta.py
spycial.egg-info/PKG-INFO
spycial.egg-info/SOURCES.txt
spycial.egg-info/dependency_links.txt
spycial.egg-info/requires.txt
spycial.egg-info/top_level.txt