Metadata-Version: 2.1
Name: spycial
Version: 0.2
Summary: Special functions written in Python and accelerated by Numba
Home-page: https://github.com/person142/spycial
Author: Josh Wilson
License: UNKNOWN
Platform: UNKNOWN
